pollev_tools/__init__.py
pollev_tools/reader.py
resources/config.ini
resources/html-styles.css
pollev_history_compiler-1.0.3.dist-info/METADATA
pollev_history_compiler-1.0.3.dist-info/WHEEL
pollev_history_compiler-1.0.3.dist-info/entry_points.txt
pollev_history_compiler-1.0.3.dist-info/top_level.txt
pollev_history_compiler-1.0.3.dist-info/RECORD
