Metadata-Version: 2.1
Name: pollev-history-compiler
Version: 1.0.3
Summary: A script for the compilation of PollEverywhere history CSV files into more usable forms.
Home-page: https://github.com/tony-zeidan/PollEvHistoryCompiler
Author: Tony Abou Zeidan
Author-email: tony.azp25@gmail.com
Classifier: Development Status :: 3 - Alpha
Classifier: Intended Audience :: Education
Classifier: Programming Language :: Python :: 3
Classifier: Programming Language :: Python :: 3.6
Classifier: Programming Language :: Python :: 3.7
Classifier: Programming Language :: Python :: 3.8
Requires-Python: >=3.6
Requires-Dist: pandas
Requires-Dist: markdownify
Requires-Dist: toml
